[
    {
        "mes": 0, 
        "id": "compost", 
        "imageUrl": "img/tareas/compost/compost01.jpg", 
        "titulo": "Preparar una nueva pila de compost"
    }, 
    {
        "mes": 5,
        "id": "esquejesLavanda", 
        "imageUrl": "img/tareas/esquejesLavanda/esquejesLavanda01.jpg", 
        "titulo": "Hacer esquejes de lavanda" 
    }, 
    {
        "mes": 5,
        "id": "esquejesRomero", 
        "imageUrl": "img/tareas/esquejesRomero/esquejesRomero01.jpg", 
        "titulo": "Hacer esquejes de romero" 
    },     
    {
        "mes": 4,
        "id": "materiaOrganica", 
        "imageUrl": "img/tareas/materiaOrganica/materiaOrganica01.jpg", 
        "titulo": "Agregar materia orgánica al suelo" 
    },
    {
        "mes": 5,
        "id": "mulching", 
        "imageUrl": "img/tareas/mulching/mulching01.jpg", 
        "titulo": "Aplicar mulching en los canteros" 
    }

]
